payment_text_parser/__init__.py
payment_text_parser/app.py
payment_text_parser/app2.py
payment_text_parser/app_test.py
payment_text_parser/predict.py
payment_text_parser/address_recognizer/__init__.py
payment_text_parser/address_recognizer/address_recognizer.py
payment_text_parser/address_recognizer/address_recognizer_utils.py
payment_text_parser/address_recognizer/shap_run.py
payment_text_parser/data/scraped_data/first_name.pickle
payment_text_parser/data/scraped_data/tfidf.pickle
payment_text_parser/data_generator/__init__.py
payment_text_parser/data_generator/data_generator.py
payment_text_parser/data_generator/data_generator_utils.py
payment_text_parser/data_generator/directories_scraping.py
payment_text_parser/data_generator/wiktionary_scraping.py
payment_text_parser/data_generator/zefix_scraping.py
payment_text_parser/entity_extractor/__init__.py
payment_text_parser/entity_extractor/entity_extractor.py
payment_text_parser/entity_extractor/entity_extractor_utils.py
payment_text_parser/entity_extractor/spacy_models.py
payment_text_parser/models/keras_models/model_concat.h5
payment_text_parser/models/keras_models/model_concat.json
payment_text_parser/models/keras_models/model_concat_metadata.pickle
payment_text_parser/models/spacy_models/custom_de_core_news_sm_LOC-ENT_100000_0_0.0.72/meta.json
payment_text_parser/models/spacy_models/custom_de_core_news_sm_LOC-ENT_100000_0_0.0.72/tokenizer
payment_text_parser/models/spacy_models/custom_de_core_news_sm_LOC-ENT_100000_0_0.0.72/ner/cfg
payment_text_parser/models/spacy_models/custom_de_core_news_sm_LOC-ENT_100000_0_0.0.72/ner/model
payment_text_parser/models/spacy_models/custom_de_core_news_sm_LOC-ENT_100000_0_0.0.72/ner/moves
payment_text_parser/models/spacy_models/custom_de_core_news_sm_LOC-ENT_100000_0_0.0.72/vocab/key2row
payment_text_parser/models/spacy_models/custom_de_core_news_sm_LOC-ENT_100000_0_0.0.72/vocab/lexemes.bin
payment_text_parser-0.0.9.dist-info/LICENSE
payment_text_parser-0.0.9.dist-info/METADATA
payment_text_parser-0.0.9.dist-info/WHEEL
payment_text_parser-0.0.9.dist-info/top_level.txt
payment_text_parser-0.0.9.dist-info/RECORD
