Metadata-Version: 2.1
Name: payment-text-parser
Version: 0.0.9
Summary: Parser for entity/address free text (based on libpostal/spacy)
Home-page: https://gitlab.com/alpina-analytics/payment_text_parser.git
Author: Pierre Oberholzer
Author-email: pierre.oberholzer@alpina-analytics.com
License: UNKNOWN
Platform: UNKNOWN
Classifier: Programming Language :: Python :: 3
Classifier: License :: OSI Approved :: GNU Affero General Public License v3
Classifier: Operating System :: OS Independent
Requires-Dist: absl-py (==0.7.1)
Requires-Dist: appnope (==0.1.0)
Requires-Dist: astor (==0.8.0)
Requires-Dist: attrs (==19.1.0)
Requires-Dist: backcall (==0.1.0)
Requires-Dist: beautifulsoup4 (==4.8.0)
Requires-Dist: blis (==0.2.4)
Requires-Dist: ccy (==1.0.0)
Requires-Dist: certifi (==2019.6.16)
Requires-Dist: chardet (==3.0.4)
Requires-Dist: Click (==7.0)
Requires-Dist: corenlp-protobuf (==3.8.0)
Requires-Dist: cycler (==0.10.0)
Requires-Dist: cymem (==2.0.2)
Requires-Dist: decorator (==4.4.0)
Requires-Dist: Faker (==2.0.1)
Requires-Dist: Flask (==1.1.1)
Requires-Dist: Flask-Cors (==3.0.8)
Requires-Dist: gast (==0.2.2)
Requires-Dist: grpcio (==1.22.0)
Requires-Dist: h5py (==2.9.0)
Requires-Dist: idna (==2.8)
Requires-Dist: imageio (==2.5.0)
Requires-Dist: ipython (==7.7.0)
Requires-Dist: ipython-genutils (==0.2.0)
Requires-Dist: itsdangerous (==1.1.0)
Requires-Dist: jedi (==0.14.1)
Requires-Dist: Jinja2 (==2.10.1)
Requires-Dist: joblib (==0.13.2)
Requires-Dist: jsonschema (==3.0.2)
Requires-Dist: Keras (==2.2.4)
Requires-Dist: Keras-Applications (==1.0.8)
Requires-Dist: Keras-Preprocessing (==1.1.0)
Requires-Dist: kiwisolver (==1.1.0)
Requires-Dist: langdetect (==1.0.7)
Requires-Dist: Markdown (==3.1.1)
Requires-Dist: MarkupSafe (==1.1.1)
Requires-Dist: mock (==3.0.5)
Requires-Dist: murmurhash (==1.0.2)
Requires-Dist: names-dataset (==1.9.0)
Requires-Dist: networkx (==2.3)
Requires-Dist: numpy (==1.17.0)
Requires-Dist: pandas (==0.24.0)
Requires-Dist: parso (==0.5.1)
Requires-Dist: pexpect (==4.7.0)
Requires-Dist: pickleshare (==0.7.5)
Requires-Dist: Pillow (==6.1.0)
Requires-Dist: plac (==0.9.6)
Requires-Dist: postal (==1.1.7)
Requires-Dist: preshed (==2.0.1)
Requires-Dist: prompt-toolkit (==2.0.9)
Requires-Dist: protobuf (==3.9.0)
Requires-Dist: ptyprocess (==0.6.0)
Requires-Dist: public (==2019.4.13)
Requires-Dist: pycountry (==19.7.15)
Requires-Dist: Pygments (==2.4.2)
Requires-Dist: pyparsing (==2.4.2)
Requires-Dist: pyrsistent (==0.15.4)
Requires-Dist: python-dateutil (==2.8.0)
Requires-Dist: pytz (==2019.2)
Requires-Dist: PyWavelets (==1.0.3)
Requires-Dist: PyYAML (==5.1.2)
Requires-Dist: query-string (==2019.4.13)
Requires-Dist: requests (==2.22.0)
Requires-Dist: scikit-image (==0.15.0)
Requires-Dist: scikit-learn (==0.21.3)
Requires-Dist: scipy (==1.3.0)
Requires-Dist: six (==1.12.0)
Requires-Dist: soupsieve (==1.9.2)
Requires-Dist: spacy (==2.1.4)
Requires-Dist: srsly (==0.0.7)
Requires-Dist: stanford-corenlp (==3.9.2)
Requires-Dist: style (==1.1.0)
Requires-Dist: tensorboard (==1.13.1)
Requires-Dist: tensorflow (==1.13.1)
Requires-Dist: tensorflow-estimator (==1.13.0)
Requires-Dist: termcolor (==1.1.0)
Requires-Dist: thinc (==7.0.8)
Requires-Dist: torch (==1.1.0)
Requires-Dist: tqdm (==4.32.2)
Requires-Dist: traitlets (==4.3.2)
Requires-Dist: Unidecode (==1.1.1)
Requires-Dist: update (==0.0.1)
Requires-Dist: urllib3 (==1.25.3)
Requires-Dist: wasabi (==0.2.2)
Requires-Dist: wcwidth (==0.1.7)
Requires-Dist: Werkzeug (==0.15.5)
